methscan/__init__.py
methscan/cli.py
methscan/diff.py
methscan/filter.py
methscan/matrix.py
methscan/numerics.py
methscan/prepare.py
methscan/profile.py
methscan/scan.py
methscan/smooth.py
methscan/utils.py
methscan-1.1.0.dist-info/LICENSE
methscan-1.1.0.dist-info/METADATA
methscan-1.1.0.dist-info/WHEEL
methscan-1.1.0.dist-info/entry_points.txt
methscan-1.1.0.dist-info/RECORD
